sensemakr/__init__.py
sensemakr/_version.py
sensemakr/bias_functions.py
sensemakr/data.py
sensemakr/main.py
sensemakr/sensitivity_bounds.py
sensemakr/sensitivity_plots.py
sensemakr/sensitivity_statistics.py
sensemakr/data/darfur.csv
sensemakr/data/references.txt
sensemakr/docs/Makefile
sensemakr/docs/conf.py
sensemakr/docs/index.rst
sensemakr/docs/make.bat
sensemakr/docs/_static/custom.css
sensemakr/docs/modules/bias_functions.rst
sensemakr/docs/modules/data.rst
sensemakr/docs/modules/index.rst
sensemakr/docs/modules/main.rst
sensemakr/docs/modules/sensitivity_bounds.rst
sensemakr/docs/modules/sensitivity_plots.rst
sensemakr/docs/modules/sensitivity_stats.rst
sensemakr/docs/notebooks/quickstart.ipynb
sensemakr/docs/notebooks/the_risks_of_informal_benchmarking.ipynb
PySensemakr-0.0.8.dist-info/LICENSE
PySensemakr-0.0.8.dist-info/METADATA
PySensemakr-0.0.8.dist-info/WHEEL
PySensemakr-0.0.8.dist-info/top_level.txt
PySensemakr-0.0.8.dist-info/RECORD
